lcgp/__init__.py
lcgp/_import_util.py
lcgp/_version.py
lcgp/covmat.py
lcgp/evaluation.py
lcgp/lcgp.py
lcgp/test.py
lcgp/tests/__init__.py
lcgp/tests/test_cov.py
lcgp/tests/test_diagnostics.py
lcgp/tests/test_initialize.py
lcgp/tests/test_training.py
lcgp-0.2.0.dist-info/licenses/LICENSE.txt
lcgp-0.2.0.dist-info/METADATA
lcgp-0.2.0.dist-info/WHEEL
lcgp-0.2.0.dist-info/top_level.txt
lcgp-0.2.0.dist-info/RECORD
