Metadata-Version: 2.4
Name: lcgp
Version: 0.2.0
Summary: Latent component Gaussian process
Author-email: Moses Chan <moses.chan@northwestern.edu>
License: The MIT License (MIT)
Project-URL: Repository, https://github.com/mosesyhc/lcgp
Classifier: Programming Language :: Python :: 3
Classifier: License :: OSI Approved :: MIT License
Classifier: Operating System :: OS Independent
Requires-Python: >=3.9
License-File: LICENSE.txt
Requires-Dist: numpy>=1.18.3
Requires-Dist: scipy>=1.10.1
Requires-Dist: tensorflow>=2.16.0
Requires-Dist: gpflow>=2.5.0
Provides-Extra: test
Requires-Dist: pytest; extra == "test"
Requires-Dist: pytest-cov; extra == "test"
Dynamic: license-file
